gdmec23120413/__init__.py
gdmec23120413-0.1.1.dist-info/METADATA
gdmec23120413-0.1.1.dist-info/WHEEL
gdmec23120413-0.1.1.dist-info/entry_points.txt
gdmec23120413-0.1.1.dist-info/RECORD
